pytest_dbx/__init__.py
pytest_dbx/common.py
pytest_dbx/fixtures.py
pytest_dbx-0.1.0.dist-info/entry_points.txt
pytest_dbx-0.1.0.dist-info/LICENSE
pytest_dbx-0.1.0.dist-info/WHEEL
pytest_dbx-0.1.0.dist-info/METADATA
pytest_dbx-0.1.0.dist-info/RECORD
