Metadata-Version: 2.1
Name: pytest-dbx
Version: 0.1.0
Summary: Pytest plugin to run unit tests for dbx (Databricks CLI extensions) related code
Home-page: https://github.com/jmeidam/pytest-dbx
Author: Jeroen Meidam
Author-email: j.meidam@gmail.com
Requires-Python: >=3.9,<4.0
Classifier: Programming Language :: Python :: 3
Classifier: Programming Language :: Python :: 3.9
Classifier: Programming Language :: Python :: 3.10
Classifier: Programming Language :: Python :: 3.11
Requires-Dist: dbx (>=0.8.7,<0.9.0)
Requires-Dist: delta-spark (==2.1.1)
Requires-Dist: ipython (>=8.5.0,<9.0.0)
Requires-Dist: pytest (>=7.1.3,<8.0.0)
Project-URL: Repository, https://github.com/jmeidam/pytest-dbx
